pyprerender/BaseEventHandler.py
pyprerender/Chrome.py
pyprerender/ParseHTMLEventHandler.py
pyprerender/__init__.py
pyprerender/pyprerender-api.py
pyprerender-0.0.9.data/scripts/pyprerender-api.py
pyprerender-0.0.9.dist-info/LICENSE
pyprerender-0.0.9.dist-info/METADATA
pyprerender-0.0.9.dist-info/WHEEL
pyprerender-0.0.9.dist-info/top_level.txt
pyprerender-0.0.9.dist-info/RECORD
