Metadata-Version: 2.1
Name: pyprerender
Version: 0.0.9
Summary: A python prerender
Home-page: https://github.com/thingiesmm/pyprerender
Author: Matas Minelga
Author-email: minematas@gmail.com
License: MIT
Platform: UNKNOWN
Classifier: Programming Language :: Python :: 3
Classifier: License :: OSI Approved :: MIT License
Classifier: Operating System :: OS Independent
Requires-Python: >=3.7
Requires-Dist: pychrome (~=0.2.3)
Requires-Dist: uvicorn (~=0.11.8)
Requires-Dist: starlette (~=0.13.8)
Requires-Dist: setuptools (~=49.6.0)
